mai_tai_mcp/__init__.py
mai_tai_mcp/backend.py
mai_tai_mcp/backoff.py
mai_tai_mcp/communication.py
mai_tai_mcp/config.py
mai_tai_mcp/errors.py
mai_tai_mcp/mode_handlers.py
mai_tai_mcp/observability.py
mai_tai_mcp/server.py
mai_tai_mcp/state.py
mai_tai_mcp/ws_client.py
mai_tai_mcp/prompts/agent_instructions.md
mai_tai_mcp-0.4.3.dist-info/METADATA
mai_tai_mcp-0.4.3.dist-info/WHEEL
mai_tai_mcp-0.4.3.dist-info/entry_points.txt
mai_tai_mcp-0.4.3.dist-info/top_level.txt
mai_tai_mcp-0.4.3.dist-info/RECORD
