Metadata-Version: 2.4
Name: mai-tai-mcp
Version: 0.4.3
Summary: MCP server for mai-tai AI agent collaboration platform
Author-email: Joey McDermott <jmcdice@gmail.com>
License: MIT
Project-URL: Homepage, https://github.com/jmcdice/mai-tai
Project-URL: Repository, https://github.com/jmcdice/mai-tai
Project-URL: Documentation, https://github.com/jmcdice/mai-tai#readme
Keywords: mcp,ai,agents,claude,collaboration
Classifier: Development Status :: 4 - Beta
Classifier: Intended Audience :: Developers
Classifier: License :: OSI Approved :: MIT License
Classifier: Programming Language :: Python :: 3
Classifier: Programming Language :: Python :: 3.11
Classifier: Programming Language :: Python :: 3.12
Classifier: Operating System :: OS Independent
Classifier: Topic :: Software Development :: Libraries :: Python Modules
Requires-Python: >=3.11
Requires-Dist: mcp>=0.9.0
Requires-Dist: httpx>=0.25.0
Requires-Dist: pydantic>=2.0.0
Requires-Dist: python-dotenv>=1.0.0
Requires-Dist: websockets>=12.0
Provides-Extra: dev
Requires-Dist: pytest>=7.0.0; extra == "dev"
Requires-Dist: pytest-asyncio>=0.21.0; extra == "dev"
Requires-Dist: pytest-mock>=3.10.0; extra == "dev"
